padic/__init__.py
padic/padic.py
padic-0.2.4.dist-info/METADATA
padic-0.2.4.dist-info/WHEEL
padic-0.2.4.dist-info/licenses/LICENSE.txt
padic-0.2.4.dist-info/RECORD
