Metadata-Version: 2.1
Name: padic
Version: 0.2.4
Summary: Package implementing p-adic numbers
Project-URL: Homepage, https://github.com/MRaczuk/padic
Author-email: MRaczuk <mraczuk@gmail.com>
License-File: LICENSE.txt
Classifier: License :: OSI Approved :: MIT License
Classifier: Operating System :: OS Independent
Classifier: Programming Language :: Python :: 3
Classifier: Topic :: Scientific/Engineering :: Mathematics
Requires-Python: >=3.7
